src/__index__.py
src/__init__.py
src/main.py
tst/__index__.py
tst/test_main.py
gepcat-1.0.0.dist-info/METADATA
gepcat-1.0.0.dist-info/WHEEL
gepcat-1.0.0.dist-info/entry_points.txt
gepcat-1.0.0.dist-info/top_level.txt
gepcat-1.0.0.dist-info/RECORD
