Metadata-Version: 2.1
Name: gepcat
Version: 1.0.0
Requires-Dist: click
Requires-Dist: toml
Provides-Extra: test
Requires-Dist: pytest ==6.2.5 ; extra == 'test'
Requires-Dist: pytest-cov ==3.0.0 ; extra == 'test'
